fsonbase/__init__.py
fsonbase/fcluster.py
fsonbase/fsonbase.py
fsonbase/mcluster.py
fsonbase-0.3.1.dist-info/LICENSE
fsonbase-0.3.1.dist-info/METADATA
fsonbase-0.3.1.dist-info/WHEEL
fsonbase-0.3.1.dist-info/top_level.txt
fsonbase-0.3.1.dist-info/RECORD
